helpscout/__init__.py
helpscout/exceptions.py
helpscout/helpscout.py
helpscout/endpoints/__init__.py
helpscout/endpoints/endpoint.py
helpscout/endpoints/mailbox.py
helpscout/endpoints/tag.py
helpscout/endpoints/team.py
helpscout/endpoints/user.py
helpscout/endpoints/webhook.py
helpscout/endpoints/workflow.py
helpscout/endpoints/conversations/__init__.py
helpscout/endpoints/conversations/attachment.py
helpscout/endpoints/conversations/conversation.py
helpscout/endpoints/conversations/custom_field.py
helpscout/endpoints/conversations/tag.py
helpscout/endpoints/conversations/thread.py
helpscout/endpoints/customers/__init__.py
helpscout/endpoints/customers/address.py
helpscout/endpoints/customers/chat_handler.py
helpscout/endpoints/customers/customer.py
helpscout/endpoints/customers/email.py
helpscout/endpoints/customers/phone.py
helpscout/endpoints/customers/social_profile.py
helpscout/endpoints/customers/website.py
helpscout/endpoints/reports/__init__.py
helpscout/endpoints/reports/company.py
helpscout/endpoints/reports/conversation.py
helpscout/endpoints/reports/doc.py
helpscout/endpoints/reports/happiness.py
helpscout/endpoints/reports/productivity.py
helpscout/endpoints/reports/report.py
helpscout/endpoints/reports/user.py
helpscout_wrapper-0.0.3.dist-info/LICENSE
helpscout_wrapper-0.0.3.dist-info/METADATA
helpscout_wrapper-0.0.3.dist-info/WHEEL
helpscout_wrapper-0.0.3.dist-info/top_level.txt
helpscout_wrapper-0.0.3.dist-info/RECORD
