Metadata-Version: 2.1
Name: helpscout-wrapper
Version: 0.0.3
Summary: HelpScout api wrapper
Home-page: https://github.com/Gogen120/helpscout
Author: Armand Kulsh
Author-email: armand.kulsh@gmail.com
License: MIT
Platform: UNKNOWN
Classifier: License :: OSI Approved :: MIT License
Classifier: Programming Language :: Python :: 3
Classifier: Programming Language :: Python :: 3.7
Requires-Dist: requests
